sqlalchemy_handler/__init__.py
sqlalchemy_handler/accessor.py
sqlalchemy_handler/api_errors.py
sqlalchemy_handler/as_dict.py
sqlalchemy_handler/date.py
sqlalchemy_handler/delete.py
sqlalchemy_handler/errors.py
sqlalchemy_handler/find_or_create.py
sqlalchemy_handler/human_ids.py
sqlalchemy_handler/populate.py
sqlalchemy_handler/save.py
sqlalchemy_handler/serialize.py
sqlalchemy_handler/soft_delete.py
SQLAlchemy_Handler-0.0.3.dist-info/LICENSE
SQLAlchemy_Handler-0.0.3.dist-info/METADATA
SQLAlchemy_Handler-0.0.3.dist-info/WHEEL
SQLAlchemy_Handler-0.0.3.dist-info/top_level.txt
SQLAlchemy_Handler-0.0.3.dist-info/RECORD
