Metadata-Version: 2.1
Name: SQLAlchemy-Handler
Version: 0.0.3
Summary: Adds SQLAlchemy support to your Flask application.
Home-page: https://github.com/betagouv/sqlalchemy-handler
Author: Erwan Ledoux
Author-email: lawanledoux@gmail.com
Maintainer: Ledoux
Maintainer-email: lawanledoux@gmail.com
License: MPL-2.0
Project-URL: Code, https://github.com/betagouv/sqlalchemy-handler
Project-URL: Issue tracker, https://github.com/betagouv/sqlalchemy-handler/issues
Platform: UNKNOWN
Classifier: Development Status :: 5 - Production/Stable
Classifier: Environment :: Web Environment
Classifier: Intended Audience :: Developers
Classifier: License :: OSI Approved :: Mozilla Public License 2.0 (MPL 2.0)
Classifier: Operating System :: OS Independent
Classifier: Programming Language :: Python
Classifier: Programming Language :: Python :: 2
Classifier: Programming Language :: Python :: 2.7
Classifier: Programming Language :: Python :: 3
Classifier: Programming Language :: Python :: 3.4
Classifier: Programming Language :: Python :: 3.5
Classifier: Programming Language :: Python :: 3.6
Classifier: Programming Language :: Python :: 3.7
Classifier: Programming Language :: Python :: Implementation :: CPython
Classifier: Programming Language :: Python :: Implementation :: PyPy
Classifier: Topic :: Internet :: WWW/HTTP :: Dynamic Content
Classifier: Topic :: Software Development :: Libraries :: Python Modules
Requires-Python: >= 2.7, != 3.0.*, != 3.1.*, != 3.2.*, != 3.3.*
Requires-Dist: Flask (>=0.10)
Requires-Dist: SQLAlchemy (>=0.8.0)
